yandex_book/__init__.py
yandex_book/models.py
yandex_book_api-0.1.2.dist-info/METADATA
yandex_book_api-0.1.2.dist-info/WHEEL
yandex_book_api-0.1.2.dist-info/top_level.txt
yandex_book_api-0.1.2.dist-info/RECORD
