Metadata-Version: 2.4
Name: yandex-book-api
Version: 0.1.2
Summary: Pydantic wrapper for Bookmate API
Home-page: https://github.com/stepan163s/yandex-book-api
Author: stepan163s
Author-email: stepan163s@yandex.ru
License: MIT
Classifier: Programming Language :: Python :: 3
Classifier: License :: OSI Approved :: MIT License
Classifier: Operating System :: OS Independent
Requires-Python: >=3.8
Requires-Dist: pydantic>=2.0
Requires-Dist: requests>=2.0
Dynamic: author
Dynamic: author-email
Dynamic: classifier
Dynamic: description
Dynamic: description-content-type
Dynamic: home-page
Dynamic: license
Dynamic: requires-dist
Dynamic: requires-python
Dynamic: summary
